bac_bank_gt/__init__.py
bac_bank_gt/models.py
bac_bank_parser_gt-0.2.3.dist-info/METADATA
bac_bank_parser_gt-0.2.3.dist-info/WHEEL
bac_bank_parser_gt-0.2.3.dist-info/top_level.txt
bac_bank_parser_gt-0.2.3.dist-info/RECORD
