Metadata-Version: 2.1
Name: bac-bank-parser-gt
Version: 0.2.3
Summary: Banco America Central (BAC) Parser
Home-page: https://github.com/gt-banks-parser/bac-gt-parser
Author: Carlos Simon
Author-email: dev@csimon.dev
License: UNKNOWN
Platform: UNKNOWN
Classifier: Programming Language :: Python :: 3.6
Classifier: Development Status :: 4 - Beta
Classifier: License :: OSI Approved :: MIT License
Classifier: Operating System :: OS Independent
Classifier: Intended Audience :: Financial and Insurance Industry
Classifier: Intended Audience :: Information Technology
Classifier: Topic :: Office/Business :: Financial
Classifier: Topic :: Utilities
Requires-Python: >=3.6
Requires-Dist: bank-base-gt (>=0.5)
Requires-Dist: html5lib (==1.1)
